securekit/__init__.py
securekit/adapters/__init__.py
securekit/adapters/django.py
securekit/adapters/fastapi.py
securekit/adapters/flask.py
securekit/cli/__init__.py
securekit/cli/main.py
securekit/crypto/__init__.py
securekit/crypto/aead.py
securekit/crypto/core.py
securekit/crypto/password.py
securekit/kms/__init__.py
securekit/kms/aws.py
securekit/kms/base.py
securekit/kms/local.py
securekit/kms/vault.py
securekit/utils/__init__.py
securekit/utils/config.py
securekit/utils/security.py
securekit-1.0.3.dist-info/licenses/LICENSE
securekit-1.0.3.dist-info/METADATA
securekit-1.0.3.dist-info/WHEEL
securekit-1.0.3.dist-info/entry_points.txt
securekit-1.0.3.dist-info/top_level.txt
securekit-1.0.3.dist-info/RECORD
